optycal/__init__.py
optycal/const.py
optycal/field.py
optycal/lib.py
optycal/material.py
optycal/multilayer.py
optycal/plot.py
optycal/samplespace.py
optycal/settings.py
optycal/surface.py
optycal/tapers.py
optycal/antennas/__init__.py
optycal/antennas/antenna.py
optycal/antennas/array.py
optycal/antennas/compiled_functions.py
optycal/antennas/interpolation_pattern.py
optycal/antennas/interpolator.py
optycal/antennas/patterns.py
optycal/antennas/tapers.py
optycal/antennas/compiled/__init__.py
optycal/antennas/compiled/antenna_single.py
optycal/geo/__init__.py
optycal/geo/align.py
optycal/geo/cs.py
optycal/geo/space.py
optycal/geo/mesh/__init__.py
optycal/geo/mesh/generators.py
optycal/geo/mesh/mesh.py
optycal/geo/mesh/parametric.py
optycal/geo/mesh/triangulate.py
optycal/solvers/__init__.py
optycal/solvers/strattonchu.py
optycal/solvers/strattonchuff.py
optycal/util/__init__.py
optycal/util/check.py
optycal/util/iterators.py
optycal/util/printing.py
optycal/viewer/__init__.py
optycal/viewer/cmap_maker.py
optycal/viewer/display.py
optycal/viewer/display_settings.py
optycal-0.2.0.dist-info/METADATA
optycal-0.2.0.dist-info/WHEEL
optycal-0.2.0.dist-info/licenses/LICENSE
optycal-0.2.0.dist-info/RECORD
