Metadata-Version: 2.4
Name: optycal
Version: 0.2.0
Summary: A Python based physical optics simulator
Project-URL: Homepage, https://github.com/FennisRobert/Optycal
Project-URL: Issues, https://github.com/FennisRobert/Optycal/issues
License-File: LICENSE
Requires-Python: >=3.10
Requires-Dist: loguru>=0.7.3
Requires-Dist: matplotlib>=3.8
Requires-Dist: numba-progress>=1.1.3
Requires-Dist: numba>=0.57.0
Requires-Dist: numpy>=1.24
Requires-Dist: pyvista>=0.45.3
Requires-Dist: rich>=14.2.0
Requires-Dist: scipy>=1.14.0
Requires-Dist: shapely>=2.0.7
